unreal_qt_stylesheet/__init__.py
unreal_qt_stylesheet/icons.qrc
unreal_qt_stylesheet/icons.rcc
unreal_qt_stylesheet/main.py
unreal_qt_stylesheet/ue.qss
unreal_qt_stylesheet/ue.scss
unreal_qt_stylesheet/icons/arrow-down-white.svg
unreal_qt_stylesheet/icons/arrow-down.svg
unreal_qt_stylesheet/icons/arrow-up-white.svg
unreal_qt_stylesheet/icons/arrow-up.svg
unreal_qt_stylesheet/icons/check.svg
unreal_qt_stylesheet/icons/cross-white.svg
unreal_qt_stylesheet/icons/cross.svg
unreal_qt_stylesheet/icons/progress-pattern.svg
unreal_qt_stylesheet/icons/radio.svg
unreal_qt_stylesheet/icons/triangle-down-white.svg
unreal_qt_stylesheet/icons/triangle-down.svg
unreal_qt_stylesheet/icons/triangle-right-white.svg
unreal_qt_stylesheet/icons/triangle-right.svg
unreal_qt_stylesheet/icons/uncheck.svg
unreal_qt_stylesheet/icons/unradio.svg
unreal_qt_stylesheet/ui/editor.ui
unreal_qt_stylesheet/ui/main.ui
unreal_qt_stylesheet/ui/progress.ui
unreal_qt_stylesheet/ui/tree.ui
unreal_qt_stylesheet-0.0.1.dist-info/LICENSE
unreal_qt_stylesheet-0.0.1.dist-info/METADATA
unreal_qt_stylesheet-0.0.1.dist-info/WHEEL
unreal_qt_stylesheet-0.0.1.dist-info/top_level.txt
unreal_qt_stylesheet-0.0.1.dist-info/RECORD
